{
  "generator-jhipster": {
    "promptValues": {
      "packageName": "com.web.tp",
      "nativeLanguage": "en"
    },
    "jhipsterVersion": "6.10.4",
    "applicationType": "monolith",
    "baseName": "TrainingProject",
    "packageName": "com.web.tp",
    "packageFolder": "com/web/tp",
    "serverPort": "8080",
    "authenticationType": "jwt",
    "cacheProvider": "ehcache",
    "enableHibernateCache": false,
    "websocket": false,
    "databaseType": "mongodb",
    "devDatabaseType": "mongodb",
    "prodDatabaseType": "mongodb",
    "searchEngine": false,
    "messageBroker": false,
    "serviceDiscoveryType": false,
    "buildTool": "gradle",
    "enableSwaggerCodegen": false,
    "jwtSecretKey": "MWU1Y2YzMWJmNzIzODY1MzBkNjY1YjA1NThiMDRjYTdkMzZiMjg2MGExMzZiM2ZkY2Y3ZThhYzg1NTQ5NDMyNTVlYzcwZjI0YjRmZDU0ZTkzNjMyOTQ2MTk5MjZiYmVkZmNhMmQxY2JkOTc3OTRmYjQ0ZGZlZmE5NmIwNjhmMmE=",
    "embeddableLaunchScript": false,
    "useSass": true,
    "clientPackageManager": "npm",
    "clientFramework": "react",
    "clientTheme": "darkly",
    "clientThemeVariant": "dark",
    "creationTimestamp": 1604575054786,
    "testFrameworks": [],
    "jhiPrefix": "jhi",
    "entitySuffix": "",
    "dtoSuffix": "DTO",
    "otherModules": [],
    "enableTranslation": true,
    "nativeLanguage": "en",
    "languages": ["en"],
    "blueprints": []
  }
}
